CHANGES.txt
DEPENDENCES.txt
README.txt
setup.py
src/ng/__init__.py
src/ng.app.mailform.egg-info/PKG-INFO
src/ng.app.mailform.egg-info/SOURCES.txt
src/ng.app.mailform.egg-info/dependency_links.txt
src/ng.app.mailform.egg-info/namespace_packages.txt
src/ng.app.mailform.egg-info/not-zip-safe
src/ng.app.mailform.egg-info/requires.txt
src/ng.app.mailform.egg-info/top_level.txt
src/ng/app/__init__.py
src/ng/app/mailform/__init__.py
src/ng/app/mailform/configure.zcml
src/ng/app/mailform/interfaces.py
src/ng/app/mailform/mailform.py
src/ng/app/mailform/mailform2formsave.py
src/ng/app/mailform/ng.app.mailform.txt
src/ng/app/mailform/browser/__init__.py
src/ng/app/mailform/browser/configure.zcml
src/ng/app/mailform/etc/ng.app.mailform-configure.zcml