Metadata-Version: 1.0
Name: ng.app.mailform
Version: 0.0.2
Summary: Editable form used to filling fields and send email
Home-page: http://www.dreambot.ru/ng.app.mailform/DreamBotZope3Releases/ng.app.mailform
Author: Andrey Orlov
Author-email: dbdt@dreambot.ru
License: GPL v2.1
Platform: UNKNOWN
Classifier: Environment :: Web Environment
Classifier: Intended Audience :: Developers
Classifier: License :: OSI Approved :: GNU General Public License (GPL)
Classifier: Programming Language :: Python
Classifier: Operating System :: OS Independent
Classifier: Topic :: Internet :: WWW/HTTP
Classifier: Framework :: Zope3
